__init__.py
twitcasting.py
twitcasting_py-0.1.5.dist-info/LICENSE
twitcasting_py-0.1.5.dist-info/METADATA
twitcasting_py-0.1.5.dist-info/WHEEL
twitcasting_py-0.1.5.dist-info/top_level.txt
twitcasting_py-0.1.5.dist-info/RECORD
