Metadata-Version: 2.1
Name: twitcasting-py
Version: 0.1.5
Summary: A unofficial python module for wrapping TwitCasting common APIs
Home-page: https://github.com/kkent030315/twitcasting-py
Author: Kento Oki
Author-email: hrn832@protonmail.com
License: UNKNOWN
Platform: UNKNOWN
Classifier: Development Status :: 5 - Production/Stable
Classifier: Topic :: Utilities
Classifier: Programming Language :: Python
Classifier: Programming Language :: Python :: 3
Classifier: Programming Language :: Python :: 3 :: Only
Classifier: Environment :: Console
Classifier: Intended Audience :: Developers
Classifier: License :: OSI Approved :: MIT License
Classifier: Operating System :: POSIX :: Linux
Classifier: Operating System :: Unix
Classifier: Operating System :: MacOS
Classifier: Operating System :: Microsoft :: Windows
Requires-Python: >=3.6
Requires-Dist: requests
Requires-Dist: bs4
